wbtools/__init__.py
wbtools/db/__init__.py
wbtools/db/abstract_manager.py
wbtools/db/afp.py
wbtools/db/antibody.py
wbtools/db/dbmanager.py
wbtools/db/expression.py
wbtools/db/gene.py
wbtools/db/generic.py
wbtools/db/paper.py
wbtools/db/person.py
wbtools/lib/__init__.py
wbtools/lib/scraping.py
wbtools/lib/timeout.py
wbtools/lib/email/__init__.py
wbtools/lib/email/generic.py
wbtools/lib/nlp/__init__.py
wbtools/lib/nlp/common.py
wbtools/lib/nlp/text_preprocessing.py
wbtools/lib/nlp/text_similarity.py
wbtools/lib/nlp/entity_extraction/__init__.py
wbtools/lib/nlp/entity_extraction/email_addresses.py
wbtools/lib/nlp/entity_extraction/ntt_extractor.py
wbtools/lib/nlp/entity_extraction/variations.py
wbtools/lib/nlp/literature_index/__init__.py
wbtools/lib/nlp/literature_index/abstract_index.py
wbtools/lib/nlp/literature_index/textpresso.py
wbtools/literature/__init__.py
wbtools/literature/corpus.py
wbtools/literature/paper.py
wbtools/literature/person.py
wbtools/utils/__init__.py
wbtools/utils/alliance.py
wbtools/utils/okta_utils.py
wbtools-3.2.0.dist-info/LICENSE
wbtools-3.2.0.dist-info/METADATA
wbtools-3.2.0.dist-info/WHEEL
wbtools-3.2.0.dist-info/top_level.txt
wbtools-3.2.0.dist-info/RECORD
