Metadata-Version: 2.1
Name: wbtools
Version: 3.2.0
Summary: Interface to WormBase (www.wormbase.org) curation data, including literature management and NLP functions
Author-email: Valerio Arnaboldi <valearna@caltech.edu>
Project-URL: Homepage, https://github.com/WormBase/wbtools
Project-URL: Repository, https://github.com/WormBase/wbtools
Classifier: Programming Language :: Python :: 3
Classifier: License :: OSI Approved :: MIT License
Classifier: Operating System :: OS Independent
Requires-Python: >=3.6
License-File: LICENSE
Requires-Dist: psycopg2-binary
Requires-Dist: numpy~=1.19.2
Requires-Dist: fabric~=2.5.0
Requires-Dist: gensim~=3.8.3
Requires-Dist: nltk~=3.5
Requires-Dist: regex~=2020.10.28
Requires-Dist: pdfminer.six==20201018
Requires-Dist: pytz~=2021.1
Requires-Dist: pandas~=1.3.3
Requires-Dist: requests~=2.31.0
Requires-Dist: python-dateutil~=2.8.2
Requires-Dist: python-dotenv~=1.0.0
Requires-Dist: grobid-client
